{"id":"xkcd.370-redwall","title":"Redwall","desc":"","updated":1200297600000,"created":1200297600000,"sources":[{"name":"xkcd","url":"https://creativecommons.org/licenses/by-nc/2.5/","license":"Creative Commons 2.5"}],"custom":{"sources":[{"name":"xkcd","url":"https://creativecommons.org/licenses/by-nc/2.5/","license":"Creative Commons 2.5"}]},"fname":"xkcd.370-redwall","type":"note","vault":{"fsPath":"vault","name":"xkcd"},"contentHash":"95a7ac192da3bb12cf2c443d6f764c26","links":[],"anchors":{"alt-text":{"type":"header","text":"Alt Text","value":"alt-text","line":14,"column":0,"depth":2}},"children":[],"parent":"3059c722-4541-4ab1-9995-d7846d39ceea","data":{}}
