{"id":"xkcd.1146-honest","title":"Honest","desc":"","updated":1355299200000,"created":1355299200000,"sources":[{"name":"xkcd","url":"https://creativecommons.org/licenses/by-nc/2.5/","license":"Creative Commons 2.5"}],"custom":{"sources":[{"name":"xkcd","url":"https://creativecommons.org/licenses/by-nc/2.5/","license":"Creative Commons 2.5"}]},"fname":"xkcd.1146-honest","type":"note","vault":{"fsPath":"vault","name":"xkcd"},"contentHash":"909fc6b02472d3a760c75f90ca8b93a8","links":[],"anchors":{"alt-text":{"type":"header","text":"Alt Text","value":"alt-text","line":14,"column":0,"depth":2}},"children":[],"parent":"3059c722-4541-4ab1-9995-d7846d39ceea","data":{}}
