{"id":"xkcd.201-christmas-gps","title":"Christmas GPS","desc":"","updated":1167033600000,"created":1167033600000,"sources":[{"name":"xkcd","url":"https://creativecommons.org/licenses/by-nc/2.5/","license":"Creative Commons 2.5"}],"custom":{"sources":[{"name":"xkcd","url":"https://creativecommons.org/licenses/by-nc/2.5/","license":"Creative Commons 2.5"}]},"fname":"xkcd.201-christmas-gps","type":"note","vault":{"fsPath":"vault","name":"xkcd"},"contentHash":"a650e5e6601b50747049697f01d1e595","links":[],"anchors":{"alt-text":{"type":"header","text":"Alt Text","value":"alt-text","line":14,"column":0,"depth":2}},"children":[],"parent":"3059c722-4541-4ab1-9995-d7846d39ceea","data":{}}
