{"id":"xkcd.507-experimentation","title":"Experimentation","desc":"","updated":1227254400000,"created":1227254400000,"sources":[{"name":"xkcd","url":"https://creativecommons.org/licenses/by-nc/2.5/","license":"Creative Commons 2.5"}],"custom":{"sources":[{"name":"xkcd","url":"https://creativecommons.org/licenses/by-nc/2.5/","license":"Creative Commons 2.5"}]},"fname":"xkcd.507-experimentation","type":"note","vault":{"fsPath":"vault","name":"xkcd"},"contentHash":"00680a3ed3b02df085e6ff18991c3c51","links":[],"anchors":{"alt-text":{"type":"header","text":"Alt Text","value":"alt-text","line":14,"column":0,"depth":2}},"children":[],"parent":"3059c722-4541-4ab1-9995-d7846d39ceea","data":{}}
