{"id":"xkcd.2416-trash-compactor-party","title":"Trash Compactor Party","desc":"","updated":1611561600000,"created":1611561600000,"sources":[{"name":"xkcd","url":"https://creativecommons.org/licenses/by-nc/2.5/","license":"Creative Commons 2.5"}],"custom":{"sources":[{"name":"xkcd","url":"https://creativecommons.org/licenses/by-nc/2.5/","license":"Creative Commons 2.5"}]},"fname":"xkcd.2416-trash-compactor-party","type":"note","vault":{"fsPath":"vault","name":"xkcd"},"contentHash":"4e36e5af9b981180661963da26281e57","links":[],"anchors":{"alt-text":{"type":"header","text":"Alt Text","value":"alt-text","line":14,"column":0,"depth":2}},"children":[],"parent":"3059c722-4541-4ab1-9995-d7846d39ceea","data":{}}
