{"id":"xkcd.113-riemann-zeta","title":"Riemann-Zeta","desc":"","updated":1149836400000,"created":1149836400000,"sources":[{"name":"xkcd","url":"https://creativecommons.org/licenses/by-nc/2.5/","license":"Creative Commons 2.5"}],"custom":{"sources":[{"name":"xkcd","url":"https://creativecommons.org/licenses/by-nc/2.5/","license":"Creative Commons 2.5"}]},"fname":"xkcd.113-riemann-zeta","type":"note","vault":{"fsPath":"vault","name":"xkcd"},"contentHash":"0e23e242fc61f0c73f84a4169d97d2c9","links":[],"anchors":{"alt-text":{"type":"header","text":"Alt Text","value":"alt-text","line":14,"column":0,"depth":2}},"children":[],"parent":"3059c722-4541-4ab1-9995-d7846d39ceea","data":{}}
