{"id":"xkcd.2230-versus-bracket","title":"Versus Bracket","desc":"","updated":1574064000000,"created":1574064000000,"sources":[{"name":"xkcd","url":"https://creativecommons.org/licenses/by-nc/2.5/","license":"Creative Commons 2.5"}],"custom":{"sources":[{"name":"xkcd","url":"https://creativecommons.org/licenses/by-nc/2.5/","license":"Creative Commons 2.5"}]},"fname":"xkcd.2230-versus-bracket","type":"note","vault":{"fsPath":"vault","name":"xkcd"},"contentHash":"58b9280498b95db01497526b1735a8e0","links":[],"anchors":{"alt-text":{"type":"header","text":"Alt Text","value":"alt-text","line":14,"column":0,"depth":2}},"children":[],"parent":"3059c722-4541-4ab1-9995-d7846d39ceea","data":{}}
